{"lastUsed":1659464308299,"path":"D:\/Eclipse-JEE\/projeler","projectCount":3,"recentFiles":[{"path":"\/JavaBootCampVideo2\/src\/oop","parentWorkspace":"D:\/Eclipse-JEE\/projeler","name":"Product.java","lastModified":1658265557801,"locationURI":"file:\/D:\/Eclipse-JEE\/projeler\/JavaBootCampVideo2\/src\/oop\/Product.java"},{"path":"\/JavaBootCampVideo1\/src\/test","parentWorkspace":"D:\/Eclipse-JEE\/projeler","name":"Info.java","lastModified":1656199980749,"locationURI":"file:\/D:\/Eclipse-JEE\/projeler\/JavaBootCampVideo1\/src\/test\/Info.java"},{"path":"\/JavaBootCampVideo2\/src\/oop","parentWorkspace":"D:\/Eclipse-JEE\/projeler","name":"OopInfo.java","lastModified":1659464330159,"locationURI":"file:\/D:\/Eclipse-JEE\/projeler\/JavaBootCampVideo2\/src\/oop\/OopInfo.java"},{"path":"\/JavaBootCampVideo1Tekrar\/src\/Video1","parentWorkspace":"D:\/Eclipse-JEE\/projeler","name":"Proje1.java","lastModified":1658020543088,"locationURI":"file:\/D:\/Eclipse-JEE\/projeler\/JavaBootCampVideo1Tekrar\/src\/Video1\/Proje1.java"}]}